Classfile /E:/====java_file/stata_algorithm/out/production/Test/jvmTest/test.class
  Last modified 2020-7-2; size 851 bytes
  MD5 checksum 99d90e8248537ceaeb3dbd9bb1ad7635
  Compiled from "test.java"
public class jvmTest.test
  minor version: 0
  major version: 52
  flags: ACC_PUBLIC, ACC_SUPER
Constant pool:
   #1 = Methodref          #13.#31        // java/lang/Object."<init>":()V
   #2 = Fieldref           #32.#33        // java/lang/System.out:Ljava/io/PrintStream;
   #3 = String             #34            // 你是傻子吗？
   #4 = Methodref          #35.#36        // java/io/PrintStream.println:(Ljava/lang/String;)V
   #5 = Long               10l
   #7 = Methodref          #37.#38        // java/lang/Thread.sleep:(J)V
   #8 = Class              #39            // java/lang/InterruptedException
   #9 = Methodref          #8.#40         // java/lang/InterruptedException.printStackTrace:()V
  #10 = String             #41            // 啊？我...
  #11 = Methodref          #42.#43        // jvmTest/Order.hello:()V
  #12 = Class              #44            // jvmTest/test
  #13 = Class              #45            // java/lang/Object
  #14 = Utf8               <init>
  #15 = Utf8               ()V
  #16 = Utf8               Code
  #17 = Utf8               LineNumberTable
  #18 = Utf8               LocalVariableTable
  #19 = Utf8               this
  #20 = Utf8               LjvmTest/test;
  #21 = Utf8               main
  #22 = Utf8               ([Ljava/lang/String;)V
  #23 = Utf8               e
  #24 = Utf8               Ljava/lang/InterruptedException;
  #25 = Utf8               args
  #26 = Utf8               [Ljava/lang/String;
  #27 = Utf8               StackMapTable
  #28 = Class              #39            // java/lang/InterruptedException
  #29 = Utf8               SourceFile
  #30 = Utf8               test.java
  #31 = NameAndType        #14:#15        // "<init>":()V
  #32 = Class              #46            // java/lang/System
  #33 = NameAndType        #47:#48        // out:Ljava/io/PrintStream;
  #34 = Utf8               你是傻子吗？
  #35 = Class              #49            // java/io/PrintStream
  #36 = NameAndType        #50:#51        // println:(Ljava/lang/String;)V
  #37 = Class              #52            // java/lang/Thread
  #38 = NameAndType        #53:#54        // sleep:(J)V
  #39 = Utf8               java/lang/InterruptedException
  #40 = NameAndType        #55:#15        // printStackTrace:()V
  #41 = Utf8               啊？我...
  #42 = Class              #56            // jvmTest/Order
  #43 = NameAndType        #57:#15        // hello:()V
  #44 = Utf8               jvmTest/test
  #45 = Utf8               java/lang/Object
  #46 = Utf8               java/lang/System
  #47 = Utf8               out
  #48 = Utf8               Ljava/io/PrintStream;
  #49 = Utf8               java/io/PrintStream
  #50 = Utf8               println
  #51 = Utf8               (Ljava/lang/String;)V
  #52 = Utf8               java/lang/Thread
  #53 = Utf8               sleep
  #54 = Utf8               (J)V
  #55 = Utf8               printStackTrace
  #56 = Utf8               jvmTest/Order
  #57 = Utf8               hello
{
  public jvmTest.test();
    descriptor: ()V
    flags: ACC_PUBLIC
    Code:
      stack=1, locals=1, args_size=1
         0: aload_0
         1: invokespecial #1                  // Method java/lang/Object."<init>":()V
         4: return
      LineNumberTable:
        line 3: 0
      LocalVariableTable:
        Start  Length  Slot  Name   Signature
            0       5     0  this   LjvmTest/test;

  public static void main(java.lang.String[]);
    descriptor: ([Ljava/lang/String;)V
    flags: ACC_PUBLIC, ACC_STATIC
    Code:
      stack=2, locals=2, args_size=1
         0: getstatic     #2                  // Field java/lang/System.out:Ljava/io/PrintStream;
         3: ldc           #3                  // String 你是傻子吗？
         5: invokevirtual #4                  // Method java/io/PrintStream.println:(Ljava/lang/String;)V
         8: ldc2_w        #5                  // long 10l
        11: invokestatic  #7                  // Method java/lang/Thread.sleep:(J)V
        14: goto          22
        17: astore_1
        18: aload_1
        19: invokevirtual #9                  // Method java/lang/InterruptedException.printStackTrace:()V
        22: getstatic     #2                  // Field java/lang/System.out:Ljava/io/PrintStream;
        25: ldc           #10                 // String 啊？我...
        27: invokevirtual #4                  // Method java/io/PrintStream.println:(Ljava/lang/String;)V
        30: invokestatic  #11                 // Method jvmTest/Order.hello:()V
        33: return
      Exception table:
         from    to  target type
             8    14    17   Class java/lang/InterruptedException
      LineNumberTable:
        line 5: 0
        line 7: 8
        line 10: 14
        line 8: 17
        line 9: 18
        line 11: 22
        line 12: 30
        line 13: 33
      LocalVariableTable:
        Start  Length  Slot  Name   Signature
           18       4     1     e   Ljava/lang/InterruptedException;
            0      34     0  args   [Ljava/lang/String;
      StackMapTable: number_of_entries = 2
        frame_type = 81 /* same_locals_1_stack_item */
          stack = [ class java/lang/InterruptedException ]
        frame_type = 4 /* same */
}
SourceFile: "test.java"
